.gitignore
qmcpy-2.2.dist-info/METADATA
qmcpy-2.2.dist-info/WHEEL
qmcpy-2.2.dist-info/entry_points.txt
qmcpy-2.2.dist-info/licenses/LICENSE
qmcpy/.DS_Store
qmcpy/__init__.py
qmcpy/accumulate_data/__init__.py
qmcpy/discrete_distribution/__init__.py
qmcpy/discrete_distribution/_c_lib/README.md
qmcpy/discrete_distribution/_c_lib/__init__.py
qmcpy/discrete_distribution/_c_lib/_c_lib.cpython-39-darwin.so
qmcpy/discrete_distribution/_c_lib/export_ctypes.h
qmcpy/discrete_distribution/_c_lib/halton_qrng.c
qmcpy/discrete_distribution/_c_lib/util.c
qmcpy/discrete_distribution/abstract_discrete_distribution.py
qmcpy/discrete_distribution/digital_net_any_bases/__init__.py
qmcpy/discrete_distribution/digital_net_any_bases/digital_net_any_bases.py
qmcpy/discrete_distribution/digital_net_any_bases/faure.py
qmcpy/discrete_distribution/digital_net_any_bases/halton.py
qmcpy/discrete_distribution/digital_net_b2/__init__.py
qmcpy/discrete_distribution/digital_net_b2/digital_net_b2.py
qmcpy/discrete_distribution/digital_net_b2/generating_matrices/joe_kuo.6.1024.npy
qmcpy/discrete_distribution/digital_net_b2/generating_matrices/joe_kuo.6.21201.npy
qmcpy/discrete_distribution/iid_std_uniform.py
qmcpy/discrete_distribution/lattice/__init__.py
qmcpy/discrete_distribution/lattice/generating_vectors/kuo.lattice-33002-1024-1048576.9125.npy
qmcpy/discrete_distribution/lattice/lattice.py
qmcpy/fast_transform/__init__.py
qmcpy/fast_transform/ft.py
qmcpy/fast_transform/ft_pytorch.py
qmcpy/fast_transform/ft_qmctoolscl.py
qmcpy/integrand/__init__.py
qmcpy/integrand/abstract_integrand.py
qmcpy/integrand/bayesian_lr_coeffs.py
qmcpy/integrand/box_integral.py
qmcpy/integrand/custom_fun.py
qmcpy/integrand/financial_option.py
qmcpy/integrand/fourbranch2d.py
qmcpy/integrand/genz.py
qmcpy/integrand/hartmann6d.py
qmcpy/integrand/ishigami.py
qmcpy/integrand/keister.py
qmcpy/integrand/linear0.py
qmcpy/integrand/multimodal2d.py
qmcpy/integrand/sensitivity_indices.py
qmcpy/integrand/sin1d.py
qmcpy/integrand/umbridge_wrapper.py
qmcpy/kernel/__init__.py
qmcpy/kernel/abstract_kernel.py
qmcpy/kernel/common_kernels.py
qmcpy-2.2.dist-info/RECORD
