Metadata-Version: 2.4
Name: qmcpy
Version: 2.2
Summary: Quasi-Monte Carlo point generators, automatic transformations, and adaptive stopping criteria
Keywords: quasi,monte,carlo,community,software,cubature,numerical,integration,discrepancy,sobol,lattice
Author: Aleksei G Sorokin, Fred Hickernell, Sou-Cheng T. Choi, Jagadeeswaran Rathinavel, Mike McCourt
License-Expression: Apache-2.0
Classifier: Development Status :: 5 - Production/Stable
Classifier: Intended Audience :: Science/Research
Classifier: Programming Language :: Python :: 3
Classifier: Topic :: Scientific/Engineering :: Mathematics
Project-URL: Documentation, https://qmcsoftware.github.io/QMCSoftware/
Project-URL: Repository, https://github.com/QMCSoftware/QMCSoftware
Project-URL: Issues, https://github.com/QMCSoftware/QMCSoftware/issues
Requires-Python: >=3.5
Requires-Dist: numpy>=1.17.0
Requires-Dist: scipy>=1.1.0
Requires-Dist: qmctoolscl>=1.1.6
Provides-Extra: torch
Requires-Dist: torch>=2.7.0; extra == "torch"
Provides-Extra: gpytorch
Requires-Dist: gpytorch>=1.7.0; extra == "gpytorch"
Provides-Extra: botorch
Requires-Dist: botorch>=0.10.0; extra == "botorch"
Provides-Extra: umbridge
Requires-Dist: umbridge>=1.2.1; extra == "umbridge"
Provides-Extra: test
Requires-Dist: pytest==8.3.5; extra == "test"
Requires-Dist: pytest-cov==6.1.1; extra == "test"
Requires-Dist: phmutest==1.0.1; extra == "test"
Requires-Dist: pytest-accept==0.1.10; extra == "test"
Requires-Dist: testbook==0.4.2; extra == "test"
Requires-Dist: psutil==5.9.5; extra == "test"
Requires-Dist: parsl==2025.7.28; extra == "test"
Requires-Dist: seaborn>=0.8; extra == "test"
Requires-Dist: scikit-learn>=1.0.0; extra == "test"
Requires-Dist: scikit-optimize; extra == "test"
Requires-Dist: ipykernel; extra == "test"
Requires-Dist: matplotlib>=3.9.0; extra == "test"
Requires-Dist: pandas>=1.3.0; extra == "test"
Requires-Dist: yfinance>=0.2.0; extra == "test"
Requires-Dist: quantlib==1.38; extra == "test"
Requires-Dist: ipywidgets==8.1.7; extra == "test"
Requires-Dist: nbconvert>=7.2.9; extra == "test"
Requires-Dist: pytest-xdist>=3.8.0; extra == "test"
Provides-Extra: test-torch
Requires-Dist: torch>=2.7.0; extra == "test-torch"
Provides-Extra: test-gpytorch
Requires-Dist: gpytorch>=1.11; extra == "test-gpytorch"
Provides-Extra: test-botorch
Requires-Dist: botorch>=0.10.0; extra == "test-botorch"
Provides-Extra: test-umbridge
Requires-Dist: umbridge>=1.2.4; extra == "test-umbridge"
Provides-Extra: docs
Requires-Dist: nbval>=0.10.0; extra == "docs"
Requires-Dist: attrs>=21.0.0; extra == "docs"
Requires-Dist: mkdocs>=1.5.0; extra == "docs"
Requires-Dist: mkdocs-material>=9.6.12; extra == "docs"
Requires-Dist: mkdocs-jupyter>=0.25.0; extra == "docs"
Requires-Dist: mkdocstrings-python>=1.16.0; extra == "docs"
Requires-Dist: mkdocs-with-pdf>=0.9.3; extra == "docs"
Requires-Dist: mkdocs-glightbox>=0.4.0; extra == "docs"
Requires-Dist: graphviz>=0.20.0; extra == "docs"
Requires-Dist: phmutest>=1.0.1; extra == "docs"
Requires-Dist: mkpdfs-mkdocs>=1.0.1; extra == "docs"
Requires-Dist: mkdocs-print-site-plugin>=2.7.2; extra == "docs"
Requires-Dist: mkdocs-exclude>=1.0.2; extra == "docs"
Requires-Dist: pylint>=2.14.4; extra == "docs"
Provides-Extra: dev
Requires-Dist: qmcpy[botorch,docs,gpytorch,test,torch,umbridge]; extra == "dev"
Requires-Dist: jupyterlab>=4.0.0; extra == "dev"
Requires-Dist: jupyterlab_execute_time>=3.2.0; extra == "dev"
Requires-Dist: ipynbname>=2025.8.0.0; extra == "dev"
Requires-Dist: sympy>=1.14.0; extra == "dev"
Requires-Dist: matplotlib>=3.9.0; extra == "dev"
Requires-Dist: tueplots>=0.2.0; extra == "dev"
Requires-Dist: pandas>=2.0.0; extra == "dev"
Requires-Dist: scikit-learn>=1.0.0; extra == "dev"
Requires-Dist: scikit-optimize>=0.10.2; extra == "dev"
Provides-Extra: class
Requires-Dist: jupyterlab>=4.0.0; extra == "class"
Requires-Dist: matplotlib>=3.9.0; extra == "class"
Requires-Dist: seaborn>=0.13.0; extra == "class"
Requires-Dist: tueplots>=0.2.0; extra == "class"
Requires-Dist: pandas>=2.0.0; extra == "class"
Requires-Dist: scikit-learn>=1.0.0; extra == "class"
Requires-Dist: scikit-optimize>=0.10.2; extra == "class"
Requires-Dist: ipynbname>=2023.2.0.0; extra == "class"
Requires-Dist: jupyterlab_execute_time>=3.1.2; extra == "class"
Requires-Dist: ipywidgets>=8.1.0; extra == "class"
Requires-Dist: statsmodels>=0.14.3; extra == "class"
Requires-Dist: tqdm>=4.66.0; extra == "class"
Requires-Dist: sympy>=1.12; extra == "class"
Requires-Dist: arviz>=0.17; extra == "class"
Requires-Dist: plotly>=5.0; extra == "class"
Requires-Dist: networkx>=3.0; extra == "class"
